{
  "meta": {
    "analyzed_at": "2026-02-03T11:00:00Z",
    "agent": "analyzer",
    "version": "2.0",
    "project": "glazura"
  },

  "inventory": {
    "basic_data": {
      "name": "Glazurnik",
      "full_name": "Glazurnik",
      "owner": null,
      "type": "posadzki przemysłowe i komercyjne",
      "city": "Zielona Góra",
      "address": "Różana 5e1, 66-016 Zielona Góra",
      "phone": "510 625 088",
      "email": null,
      "hours": "do 16:00",
      "nip": null
    },
    "reviews": {
      "count": 0,
      "average_rating": null,
      "sources": [],
      "quality": "BRAK — honest selling wymagany"
    },
    "visual_materials": {
      "logo": {
        "exists": false,
        "source": null,
        "quality": null
      },
      "photos": {
        "count": 4,
        "source": "klient",
        "types": [
          "hala przemysłowa (1)",
          "warsztat samochodowy (1)",
          "salon/serwis samochodowy (1)",
          "przestrzeń komercyjna (1)"
        ],
        "quality": "good - profesjonalne realizacje przemysłowe"
      }
    },
    "credentials": {
      "years_in_business": null,
      "certyfikaty": []
    },
    "missing": ["opinie", "email", "NIP", "lata działalności", "imię właściciela"]
  },

  "review_analysis": {
    "total_reviews": 0,
    "average_rating": null,
    "praise_themes": [],
    "criticism_themes": [],
    "emotional_tone": null,
    "customer_language": null,
    "best_quotes": [],
    "note": "BRAK OPINII - Tier 4 honest selling dla tej sekcji"
  },

  "photos_analysis": {
    "summary": "4 zdjęcia pokazują WYRAŹNĄ specjalizację przemysłową — Tier 2",
    "categories": [
      {
        "category": "Hala przemysłowa",
        "count": 1,
        "style": "industrial, szare płytki, duża skala",
        "estimated_area": "500+ m²",
        "quality": "high",
        "type": "B2B"
      },
      {
        "category": "Warsztat samochodowy",
        "count": 1,
        "style": "industrial, podnośniki hydrauliczne",
        "quality": "high",
        "type": "B2B - motoryzacja"
      },
      {
        "category": "Salon/serwis samochodowy",
        "count": 1,
        "style": "dealership, samochody premium",
        "estimated_area": "800+ m²",
        "quality": "high",
        "type": "B2B - motoryzacja premium"
      },
      {
        "category": "Przestrzeń komercyjna",
        "count": 1,
        "style": "modern, duży format, LED, szkło",
        "quality": "high",
        "type": "B2B - komercyjne"
      }
    ],
    "specialization_detected": "Posadzki przemysłowe i komercyjne (B2B)",
    "NOT_detected": ["łazienki", "mieszkania", "B2C"],
    "photo_gaps": ["brak zdjęć zespołu", "brak before/after"]
  },

  "usp": [
    {
      "id": 1,
      "statement": "Specjalizacja przemysłowa (nie łazienki)",
      "evidence_strength": "strong",
      "type": "visible_specialization",
      "proof": "4/4 zdjęć to obiekty przemysłowe/komercyjne, 0 łazienek",
      "uniqueness": "WYRÓŻNIK - większość glazurników robi łazienki"
    },
    {
      "id": 2,
      "statement": "Duże powierzchnie (500-1000+ m²)",
      "evidence_strength": "strong",
      "type": "visible_specialization",
      "proof": "Zdjęcia pokazują hale i salony o dużym metrażu",
      "uniqueness": "Nie każdy glazurnik umie robić duże powierzchnie"
    },
    {
      "id": 3,
      "statement": "Klienci B2B (dealerzy, hale)",
      "evidence_strength": "strong",
      "type": "visible_specialization",
      "proof": "Salon samochodowy, hala przemysłowa - to nie klienci indywidualni",
      "uniqueness": "Portfolio B2B buduje wiarygodność dla kolejnych klientów B2B"
    },
    {
      "id": 4,
      "statement": "Płytki odporne na obciążenia",
      "evidence_strength": "medium",
      "type": "implied",
      "proof": "Serwisy samochodowe = olej, opony, podnośniki = wymagania techniczne",
      "uniqueness": "Wymaga wiedzy o płytkach przemysłowych"
    }
  ],

  "business_profile": {
    "identity_statement": "Glazurnik specjalizujący się w posadzkach przemysłowych i komercyjnych — hale, serwisy samochodowe, showroomy",
    "key_strengths": ["specjalizacja przemysłowa", "duże powierzchnie", "klienci B2B"],
    "personality_traits": ["konkretny", "profesjonalny", "techniczny"],
    "customer_type": "B2B (dealerzy samochodowi, właściciele hal, deweloperzy)",
    "market_position": "niszowy specjalista - premium B2B"
  },

  "tone_recommendation": {
    "style": "konkretny_techniczny",
    "description": "Ton rzeczowy, techniczny, bez lania wody. Klient B2B szuka fachowca który rozumie wymagania przemysłowe.",
    "warmth_level": 2,
    "formality_level": 3,
    "characteristics": [
      "Konkretne liczby (m², czas)",
      "Techniczne szczegóły (odporność, obciążenia)",
      "Bez 'pasji' i 'marzeń' - to B2B",
      "Referencje obiektowe"
    ],
    "example_headlines": [
      "Posadzki przemysłowe. Nie łazienki. Zielona Góra.",
      "Hale, serwisy, showroomy. 500 m² to standard.",
      "Płytki które wytrzymają podnośnik i olej."
    ],
    "words_to_use": ["posadzki przemysłowe", "hale", "serwisy", "m²", "odporność", "obciążenia"],
    "words_to_avoid": ["łazienki", "pasja", "marzenia", "kompleksowo", "indywidualne podejście"]
  },

  "design_recommendation": {
    "direction": "INDUSTRIAL",
    "confidence": "high",
    "reasoning": [
      "Specjalizacja przemysłowa = estetyka industrialna",
      "Klienci B2B = profesjonalny, rzeczowy wygląd",
      "Zdjęcia: szare płytki, stal, beton = paleta industrialna"
    ],
    "suggested_palette": {
      "primary": "#374151",
      "primary_dark": "#1F2937",
      "accent": "#F59E0B",
      "bg": "#F9FAFB",
      "bg_alt": "#F3F4F6",
      "text": "#111827",
      "text_muted": "#6B7280"
    }
  },

  "uniqueness_analysis": {
    "tier": 2,
    "tier_name": "visible_specialization",
    "confidence": "high",

    "tier_1_check": {
      "found": false,
      "checked": ["nagrody", "certyfikaty", "opinie 5.0"],
      "notes": "Brak opinii, brak certyfikatów"
    },

    "tier_2_check": {
      "found": true,
      "type": "photo_specialization",
      "evidence": [
        "4/4 zdjęć to obiekty przemysłowe/komercyjne",
        "0 zdjęć łazienek/mieszkań",
        "Hale, serwisy samochodowe, showroomy",
        "Duże powierzchnie (500-1000+ m²)",
        "KONTRAST z typowym glazurnikiem (łazienki)"
      ],
      "suggested_hook": "Posadzki przemysłowe. Nie łazienki. Zielona Góra."
    },

    "tier_3_check": {
      "found": false,
      "notes": "Brak danych o procesie"
    },

    "tier_4_fallback": {
      "needed": true,
      "where": "sekcja Opinie i FAQ",
      "weaknesses_to_address": ["brak_opinii"],
      "honest_selling_hook": "Realizacje mówią. Zadzwoń, pokażę więcej."
    },

    "recommended_hook": {
      "main": "Posadzki przemysłowe. Nie łazienki. Zielona Góra.",
      "alternative_1": "Hale, serwisy, showroomy. 500 m² to standard.",
      "alternative_2": "Typowy glazurnik robi łazienki. Ja robię hale.",
      "avoid": [
        "Profesjonalny glazurnik",
        "Kompleksowe usługi glazurnicze",
        "Układanie płytek Zielona Góra"
      ]
    },

    "hooks_to_avoid": [
      "Profesjonalne układanie płytek",
      "Kompleksowe usługi",
      "Glazurnik z pasją",
      "Indywidualne podejście"
    ]
  },

  "sections_recommendation": [
    {
      "id": 1,
      "name": "Hero",
      "purpose": "Tier 2 hook - specjalizacja przemysłowa",
      "content_notes": "Od razu pozycjonowanie: NIE łazienki",
      "photo_need": "hala lub salon samochodowy"
    },
    {
      "id": 2,
      "name": "Problem → Rozwiązanie",
      "purpose": "Dlaczego nie każdy glazurnik",
      "content_notes": "500 m² to inna liga niż łazienka 4 m²"
    },
    {
      "id": 3,
      "name": "Specjalizacja",
      "purpose": "Co robimy (i czego NIE)",
      "content_notes": "Hale, serwisy, showroomy. NIE: łazienki, mieszkania"
    },
    {
      "id": 4,
      "name": "Realizacje",
      "purpose": "Portfolio przemysłowe",
      "content_notes": "4 zdjęcia z opisami technicznymi",
      "photo_need": "wszystkie 4 zdjęcia"
    },
    {
      "id": 5,
      "name": "Dlaczego przemysłowe",
      "purpose": "USP techniczne",
      "content_notes": "Odporność, obciążenia, duże powierzchnie"
    },
    {
      "id": 6,
      "name": "FAQ",
      "purpose": "Obiekcje B2B + honest selling (brak opinii)",
      "content_notes": "Pytanie o referencje z honest selling"
    },
    {
      "id": 7,
      "name": "Kontakt",
      "purpose": "CTA B2B",
      "content_notes": "Telefon + adres"
    }
  ],

  "warnings": [
    "BRAK OPINII — honest selling wymagany w FAQ",
    "Brak imienia właściciela — personalizacja ograniczona",
    "Brak email — tylko telefon jako kontakt",
    "Brak lat działalności — nie używać 'doświadczenie' bez konkretów"
  ],

  "confidence_score": 0.82,

  "REASONING": {
    "uniqueness_tier": {
      "chosen": 2,
      "why": "Zdjęcia pokazują WYRAŹNĄ specjalizację przemysłową. 4/4 zdjęć to hale/serwisy/showroomy. 0 łazienek. To jest unikalny kąt który wyróżnia od 95% glazurników."
    },
    "hook_strategy": {
      "approach": "KONTRAST",
      "why": "Pozycjonowanie przez negację: 'Nie łazienki' natychmiast wyróżnia. Klient B2B szukający glazurnika do hali od razu wie że trafił."
    },
    "honest_selling": {
      "needed": true,
      "where": "FAQ pytanie o referencje/opinie",
      "approach": "Realizacje mówią same za siebie. Zadzwoń, pokażę więcej zdjęć."
    }
  }
}
